<annotation>
	<folimageser>images</folimageser>
	<filename>383.jpg</filename>
	<path>/home/srikanth/Desktop/winimagesows_projects/imagesjango/imagesata_cars/images/383.jpg</path>
	<source>
		<imagesatabase>Unknown</imagesatabase>
	</source>
	<size>
		<wiimagesth>2432</wiimagesth>
		<height>1368</height>
		<imagesepth>3</imagesepth>
	</size>
	<segmenteimages>0</segmenteimages>
	<object>
		<name>number_plate</name>
		<pose>Unspecifieimages</pose>
		<truncateimages>0</truncateimages>
		<imagesifficult>0</imagesifficult>
		<bnimagesbox>
			<xmin>795</xmin>
			<ymin>751</ymin>
			<xmax>1095</xmax>
			<ymax>840</ymax>
		</bnimagesbox>
	</object>
</annotation>
